{"type":"Topology","arcs":[[[103,130],[0,-13]],[[103,117],[-16,0]],[[87,117],[0,23]],[[87,140],[16,-10]],[[132,1102],[85,0],[0,-89],[86,-2],[-1,-137],[83,1],[-1,-46],[81,-102],[89,-15],[1,-109],[-63,-2],[-3,-276],[212,-1],[0,-321],[-213,1],[-128,22],[0,92],[-54,0],[1,-115],[-244,-3],[-2,116],[-42,-1],[-19,298],[340,3],[2,92],[-43,0],[0,137],[-84,-1],[-1,-91],[-213,-3],[1,138],[64,1],[108,92],[-150,-1],[1,230],[-22,91],[129,1]],[[103,117],[0,13]],[[87,140],[0,-23]],[[642,1333],[-44,-45]],[[598,1288],[0,-69],[-127,-47],[-106,0],[0,80],[43,0],[21,-57],[86,92],[63,1],[64,45]]],"transform":{"scale":[0.0004371169392523313,0.0003159509502924008],"translate":[-97.3701782,39.132206]},"objects":{"temp_20027":{"type":"GeometryCollection","geometries":[{"arcs":[[0,1,2,3]],"type":"Polygon","properties":{"pws_id":"KS2002706"}},{"type":null,"properties":{"pws_id":"KS2002708"}},{"type":null,"properties":{"pws_id":"KS2002702"}},{"arcs":[[4],[-2,5,-4,6]],"type":"Polygon","properties":{"pws_id":"KS2002710"}},{"arcs":[[7,8]],"type":"Polygon","properties":{"pws_id":"KS2002704"}},{"type":null,"properties":{"pws_id":"KS2002701"}},{"type":null,"properties":{"pws_id":"KS2002705"}},{"type":null,"properties":{"pws_id":"KS2002703"}},{"type":null,"properties":{"pws_id":"KS2002709"}}]}}}