{"type":"Topology","arcs":[[[2827,699],[69,-48],[119,9],[25,-56],[102,17],[7,43],[172,15],[-259,-148],[-32,-92],[-56,-68],[-143,71],[-3,74],[-80,47],[79,136]],[[175,157],[-53,-92],[-122,-4],[2,167],[59,-1],[1,107],[123,0],[22,-133]],[[207,201],[-32,-44]],[[207,201],[112,42],[39,-48],[-2,-127],[-45,-68],[-80,68],[-57,-1],[1,90]],[[1731,340],[88,38],[40,-143],[-117,-25],[-11,130]]],"transform":{"scale":[0.00018361737428485603,0.00011971952309985056],"translate":[-80.1761364,41.8622437]},"objects":{"temp_42049":{"type":"GeometryCollection","geometries":[{"arcs":[[0]],"type":"Polygon","properties":{"pws_id":"PA6250012"}},{"arcs":[[1,2]],"type":"Polygon","properties":{"pws_id":"PA6250092"}},{"arcs":[[3,-3]],"type":"Polygon","properties":{"pws_id":"PA6250022"}},{"arcs":[[4]],"type":"Polygon","properties":{"pws_id":"PA6250064"}},{"type":null,"properties":{"pws_id":"PA6250065"}},{"type":null,"properties":{"pws_id":"PA6250094"}},{"type":null,"properties":{"pws_id":"PA6250067"}},{"type":null,"properties":{"pws_id":"PA6250017"}},{"type":null,"properties":{"pws_id":"PA6250089"}},{"type":null,"properties":{"pws_id":"PA6250020"}},{"type":null,"properties":{"pws_id":"PA6250008"}},{"type":null,"properties":{"pws_id":"PA6250021"}},{"type":null,"properties":{"pws_id":"PA6250018"}},{"type":null,"properties":{"pws_id":"PA6250023"}}]}}}