{"type":"Topology","arcs":[[[555,960],[67,31],[140,-1],[-29,-55],[-60,-35],[-77,0],[-41,60]],[[74,789],[-74,0],[0,210],[61,-29],[120,11],[0,58],[60,-1],[89,53],[86,-48],[27,-64],[0,-84],[-82,0],[0,-151],[-111,-22],[-30,-87],[-124,0],[-22,154]],[[634,460],[-35,32]],[[599,492],[13,78]],[[612,570],[18,31]],[[630,601],[28,100],[170,-1],[-37,-69],[-1,-188],[-156,17]],[[599,492],[-90,-24]],[[509,468],[7,65],[50,13]],[[566,546],[46,24]],[[634,460],[17,-147],[-87,-100],[-84,1],[20,131],[-42,33],[0,59],[51,31]],[[614,126],[42,3]],[[656,129],[-7,-62],[-39,0],[-9,-67],[-57,6],[3,62],[87,0],[-20,58]],[[614,126],[-19,-36],[-132,2],[63,85],[82,29],[48,-77]],[[566,546],[-53,-10],[-9,120],[36,40],[90,-95]]],"transform":{"scale":[0.0005233954106280348,0.0004416255728689222],"translate":[-95.85086310000001,36.1035674]},"objects":{"temp_40131":{"type":"GeometryCollection","geometries":[{"type":null,"properties":{"pws_id":"OK3006631"}},{"type":null,"properties":{"pws_id":"OK3006629"}},{"arcs":[[0]],"type":"Polygon","properties":{"pws_id":"OK1021504"}},{"arcs":[[1]],"type":"Polygon","properties":{"pws_id":"OK1021506"}},{"arcs":[[2,3,4,5]],"type":"Polygon","properties":{"pws_id":"OK3006604"}},{"arcs":[[-4,6,7,8]],"type":"Polygon","properties":{"pws_id":"OK3006605"}},{"arcs":[[-7,-3,9]],"type":"Polygon","properties":{"pws_id":"OK3006606"}},{"arcs":[[10,11]],"type":"Polygon","properties":{"pws_id":"OK3006612"}},{"arcs":[[-11,12]],"type":"Polygon","properties":{"pws_id":"OK3006628"}},{"arcs":[[-9,13,-5]],"type":"Polygon","properties":{"pws_id":"OK3006603"}}]}}}