{"type":"Topology","arcs":[[[351,15],[-175,24],[14,75],[-47,-13],[0,91],[-143,1],[1,82],[136,1],[-53,82],[61,0],[2,165],[48,0],[0,41],[-48,0],[1,124],[95,0],[-1,-114],[13,-31],[62,-58],[30,0],[74,-61],[7,-232],[-63,-96],[39,-17],[119,-1],[0,-45],[-86,-33],[-86,15]]],"transform":{"scale":[0.00005003441682602797,0.00004345494186046263],"translate":[-94.7503307,40.9780383]},"objects":{"temp_19003":{"type":"GeometryCollection","geometries":[{"arcs":[[0]],"type":"Polygon","properties":{"pws_id":"IA0220075"}}]}}}